Metadata-Version: 2.1
Name: gpustat-web
Version: 0.3.0
Summary: A web interface of gpustat --- consolidate status across multiple nodes.
Home-page: https://github.com/wookayin/gpustat-web
Author: Jongwook Choi
Author-email: wookayin@gmail.com
License: MIT
Keywords: nvidia-smi gpu cuda monitoring gpustat
Classifier: Development Status :: 4 - Beta
Classifier: License :: OSI Approved :: MIT License
Classifier: Operating System :: POSIX :: Linux
Classifier: Programming Language :: Python :: 3
Classifier: Topic :: System :: Monitoring
Requires-Python: >=3.6
Provides-Extra: test
License-File: LICENSE
